itly_plugin_segment/__init__.py
itly_plugin_segment/_segment_plugin.py
itly_plugin_segment-0.1.9.dist-info/WHEEL
itly_plugin_segment-0.1.9.dist-info/METADATA
itly_plugin_segment-0.1.9.dist-info/RECORD
